README.md
setup.py
parse_nmap.egg-info/PKG-INFO
parse_nmap.egg-info/SOURCES.txt
parse_nmap.egg-info/dependency_links.txt
parse_nmap.egg-info/entry_points.txt
parse_nmap.egg-info/requires.txt
parse_nmap.egg-info/top_level.txt
parsenmap/__init__.py
parsenmap/export.py
parsenmap/filter.py
parsenmap/main.py
parsenmap/printer.py
parsenmap/util.py