Metadata-Version: 1.0
Name: parse-nmap
Version: 0.2.0
Summary: Parse-nmap is a tool which parses nmap scan results (only XML) from a file. By using parse-nmap it is possible to filter the results by platform or ip or to generate target lists.
Home-page: https://bitbucket.org/cbless/parse-nmap
Author: Christoph Bless
Author-email: bitbucket@cbless.de
License:  GPLv3
Platform: UNKNOWN
